[
  {
    "id": "取手_1R",
    "track": "取手",
    "race_num": "1R",
    "time_str": "08:25",
    "deadline": "2026-04-21T08:25:00+09:00"
  },
  {
    "id": "取手_2R",
    "track": "取手",
    "race_num": "2R",
    "time_str": "08:45",
    "deadline": "2026-04-21T08:45:00+09:00"
  },
  {
    "id": "取手_3R",
    "track": "取手",
    "race_num": "3R",
    "time_str": "09:06",
    "deadline": "2026-04-21T09:06:00+09:00"
  },
  {
    "id": "取手_4R",
    "track": "取手",
    "race_num": "4R",
    "time_str": "09:27",
    "deadline": "2026-04-21T09:27:00+09:00"
  },
  {
    "id": "取手_5R",
    "track": "取手",
    "race_num": "5R",
    "time_str": "09:48",
    "deadline": "2026-04-21T09:48:00+09:00"
  },
  {
    "id": "取手_6R",
    "track": "取手",
    "race_num": "6R",
    "time_str": "10:09",
    "deadline": "2026-04-21T10:09:00+09:00"
  },
  {
    "id": "取手_7R",
    "track": "取手",
    "race_num": "7R",
    "time_str": "10:30",
    "deadline": "2026-04-21T10:30:00+09:00"
  },
  {
    "id": "武雄_1R",
    "track": "武雄",
    "race_num": "1R",
    "time_str": "10:40",
    "deadline": "2026-04-21T10:40:00+09:00"
  },
  {
    "id": "小松島_1R",
    "track": "小松島",
    "race_num": "1R",
    "time_str": "10:54",
    "deadline": "2026-04-21T10:54:00+09:00"
  },
  {
    "id": "sanyou_1R",
    "track": "sanyou",
    "race_num": "1R",
    "time_str": "10:54",
    "deadline": "2026-04-21T10:54:00+09:00"
  },
  {
    "id": "武雄_2R",
    "track": "武雄",
    "race_num": "2R",
    "time_str": "11:09",
    "deadline": "2026-04-21T11:09:00+09:00"
  },
  {
    "id": "sanyou_2R",
    "track": "sanyou",
    "race_num": "2R",
    "time_str": "11:19",
    "deadline": "2026-04-21T11:19:00+09:00"
  },
  {
    "id": "小松島_2R",
    "track": "小松島",
    "race_num": "2R",
    "time_str": "11:24",
    "deadline": "2026-04-21T11:24:00+09:00"
  },
  {
    "id": "武雄_3R",
    "track": "武雄",
    "race_num": "3R",
    "time_str": "11:39",
    "deadline": "2026-04-21T11:39:00+09:00"
  },
  {
    "id": "sanyou_3R",
    "track": "sanyou",
    "race_num": "3R",
    "time_str": "11:45",
    "deadline": "2026-04-21T11:45:00+09:00"
  },
  {
    "id": "小松島_3R",
    "track": "小松島",
    "race_num": "3R",
    "time_str": "11:54",
    "deadline": "2026-04-21T11:54:00+09:00"
  },
  {
    "id": "武雄_4R",
    "track": "武雄",
    "race_num": "4R",
    "time_str": "12:09",
    "deadline": "2026-04-21T12:09:00+09:00"
  },
  {
    "id": "sanyou_4R",
    "track": "sanyou",
    "race_num": "4R",
    "time_str": "12:13",
    "deadline": "2026-04-21T12:13:00+09:00"
  },
  {
    "id": "小松島_4R",
    "track": "小松島",
    "race_num": "4R",
    "time_str": "12:24",
    "deadline": "2026-04-21T12:24:00+09:00"
  },
  {
    "id": "武雄_5R",
    "track": "武雄",
    "race_num": "5R",
    "time_str": "12:39",
    "deadline": "2026-04-21T12:39:00+09:00"
  },
  {
    "id": "sanyou_5R",
    "track": "sanyou",
    "race_num": "5R",
    "time_str": "12:41",
    "deadline": "2026-04-21T12:41:00+09:00"
  },
  {
    "id": "小松島_5R",
    "track": "小松島",
    "race_num": "5R",
    "time_str": "12:54",
    "deadline": "2026-04-21T12:54:00+09:00"
  },
  {
    "id": "武雄_6R",
    "track": "武雄",
    "race_num": "6R",
    "time_str": "13:09",
    "deadline": "2026-04-21T13:09:00+09:00"
  },
  {
    "id": "sanyou_6R",
    "track": "sanyou",
    "race_num": "6R",
    "time_str": "13:11",
    "deadline": "2026-04-21T13:11:00+09:00"
  },
  {
    "id": "小松島_6R",
    "track": "小松島",
    "race_num": "6R",
    "time_str": "13:24",
    "deadline": "2026-04-21T13:24:00+09:00"
  },
  {
    "id": "武雄_7R",
    "track": "武雄",
    "race_num": "7R",
    "time_str": "13:39",
    "deadline": "2026-04-21T13:39:00+09:00"
  },
  {
    "id": "sanyou_7R",
    "track": "sanyou",
    "race_num": "7R",
    "time_str": "13:41",
    "deadline": "2026-04-21T13:41:00+09:00"
  },
  {
    "id": "小松島_7R",
    "track": "小松島",
    "race_num": "7R",
    "time_str": "13:54",
    "deadline": "2026-04-21T13:54:00+09:00"
  },
  {
    "id": "武雄_8R",
    "track": "武雄",
    "race_num": "8R",
    "time_str": "14:09",
    "deadline": "2026-04-21T14:09:00+09:00"
  },
  {
    "id": "sanyou_8R",
    "track": "sanyou",
    "race_num": "8R",
    "time_str": "14:12",
    "deadline": "2026-04-21T14:12:00+09:00"
  },
  {
    "id": "小松島_8R",
    "track": "小松島",
    "race_num": "8R",
    "time_str": "14:24",
    "deadline": "2026-04-21T14:24:00+09:00"
  },
  {
    "id": "武雄_9R",
    "track": "武雄",
    "race_num": "9R",
    "time_str": "14:39",
    "deadline": "2026-04-21T14:39:00+09:00"
  },
  {
    "id": "sanyou_9R",
    "track": "sanyou",
    "race_num": "9R",
    "time_str": "14:44",
    "deadline": "2026-04-21T14:44:00+09:00"
  },
  {
    "id": "小松島_9R",
    "track": "小松島",
    "race_num": "9R",
    "time_str": "14:54",
    "deadline": "2026-04-21T14:54:00+09:00"
  },
  {
    "id": "武雄_10R",
    "track": "武雄",
    "race_num": "10R",
    "time_str": "15:09",
    "deadline": "2026-04-21T15:09:00+09:00"
  },
  {
    "id": "sanyou_10R",
    "track": "sanyou",
    "race_num": "10R",
    "time_str": "15:16",
    "deadline": "2026-04-21T15:16:00+09:00"
  },
  {
    "id": "小松島_10R",
    "track": "小松島",
    "race_num": "10R",
    "time_str": "15:24",
    "deadline": "2026-04-21T15:24:00+09:00"
  },
  {
    "id": "武雄_11R",
    "track": "武雄",
    "race_num": "11R",
    "time_str": "15:39",
    "deadline": "2026-04-21T15:39:00+09:00"
  },
  {
    "id": "静岡_1R",
    "track": "静岡",
    "race_num": "1R",
    "time_str": "15:46",
    "deadline": "2026-04-21T15:46:00+09:00"
  },
  {
    "id": "小松島_11R",
    "track": "小松島",
    "race_num": "11R",
    "time_str": "15:54",
    "deadline": "2026-04-21T15:54:00+09:00"
  },
  {
    "id": "sanyou_11R",
    "track": "sanyou",
    "race_num": "11R",
    "time_str": "15:54",
    "deadline": "2026-04-21T15:54:00+09:00"
  },
  {
    "id": "松山_1R",
    "track": "松山",
    "race_num": "1R",
    "time_str": "16:01",
    "deadline": "2026-04-21T16:01:00+09:00"
  },
  {
    "id": "静岡_2R",
    "track": "静岡",
    "race_num": "2R",
    "time_str": "16:09",
    "deadline": "2026-04-21T16:09:00+09:00"
  },
  {
    "id": "武雄_12R",
    "track": "武雄",
    "race_num": "12R",
    "time_str": "16:16",
    "deadline": "2026-04-21T16:16:00+09:00"
  },
  {
    "id": "松山_2R",
    "track": "松山",
    "race_num": "2R",
    "time_str": "16:23",
    "deadline": "2026-04-21T16:23:00+09:00"
  },
  {
    "id": "静岡_3R",
    "track": "静岡",
    "race_num": "3R",
    "time_str": "16:33",
    "deadline": "2026-04-21T16:33:00+09:00"
  },
  {
    "id": "sanyou_12R",
    "track": "sanyou",
    "race_num": "12R",
    "time_str": "16:33",
    "deadline": "2026-04-21T16:33:00+09:00"
  },
  {
    "id": "松山_3R",
    "track": "松山",
    "race_num": "3R",
    "time_str": "16:45",
    "deadline": "2026-04-21T16:45:00+09:00"
  },
  {
    "id": "静岡_4R",
    "track": "静岡",
    "race_num": "4R",
    "time_str": "16:57",
    "deadline": "2026-04-21T16:57:00+09:00"
  },
  {
    "id": "松山_4R",
    "track": "松山",
    "race_num": "4R",
    "time_str": "17:09",
    "deadline": "2026-04-21T17:09:00+09:00"
  },
  {
    "id": "静岡_5R",
    "track": "静岡",
    "race_num": "5R",
    "time_str": "17:21",
    "deadline": "2026-04-21T17:21:00+09:00"
  },
  {
    "id": "松山_5R",
    "track": "松山",
    "race_num": "5R",
    "time_str": "17:33",
    "deadline": "2026-04-21T17:33:00+09:00"
  },
  {
    "id": "静岡_6R",
    "track": "静岡",
    "race_num": "6R",
    "time_str": "17:45",
    "deadline": "2026-04-21T17:45:00+09:00"
  },
  {
    "id": "松山_6R",
    "track": "松山",
    "race_num": "6R",
    "time_str": "17:57",
    "deadline": "2026-04-21T17:57:00+09:00"
  },
  {
    "id": "静岡_7R",
    "track": "静岡",
    "race_num": "7R",
    "time_str": "18:09",
    "deadline": "2026-04-21T18:09:00+09:00"
  },
  {
    "id": "松山_7R",
    "track": "松山",
    "race_num": "7R",
    "time_str": "18:21",
    "deadline": "2026-04-21T18:21:00+09:00"
  },
  {
    "id": "静岡_8R",
    "track": "静岡",
    "race_num": "8R",
    "time_str": "18:33",
    "deadline": "2026-04-21T18:33:00+09:00"
  },
  {
    "id": "松山_8R",
    "track": "松山",
    "race_num": "8R",
    "time_str": "18:45",
    "deadline": "2026-04-21T18:45:00+09:00"
  },
  {
    "id": "川口_1R",
    "track": "川口",
    "race_num": "1R",
    "time_str": "18:48",
    "deadline": "2026-04-21T18:48:00+09:00"
  },
  {
    "id": "静岡_9R",
    "track": "静岡",
    "race_num": "9R",
    "time_str": "18:57",
    "deadline": "2026-04-21T18:57:00+09:00"
  },
  {
    "id": "松山_9R",
    "track": "松山",
    "race_num": "9R",
    "time_str": "19:09",
    "deadline": "2026-04-21T19:09:00+09:00"
  },
  {
    "id": "川口_2R",
    "track": "川口",
    "race_num": "2R",
    "time_str": "19:13",
    "deadline": "2026-04-21T19:13:00+09:00"
  },
  {
    "id": "静岡_10R",
    "track": "静岡",
    "race_num": "10R",
    "time_str": "19:21",
    "deadline": "2026-04-21T19:21:00+09:00"
  },
  {
    "id": "松山_10R",
    "track": "松山",
    "race_num": "10R",
    "time_str": "19:33",
    "deadline": "2026-04-21T19:33:00+09:00"
  },
  {
    "id": "川口_3R",
    "track": "川口",
    "race_num": "3R",
    "time_str": "19:38",
    "deadline": "2026-04-21T19:38:00+09:00"
  },
  {
    "id": "静岡_11R",
    "track": "静岡",
    "race_num": "11R",
    "time_str": "19:46",
    "deadline": "2026-04-21T19:46:00+09:00"
  },
  {
    "id": "松山_11R",
    "track": "松山",
    "race_num": "11R",
    "time_str": "19:59",
    "deadline": "2026-04-21T19:59:00+09:00"
  },
  {
    "id": "川口_4R",
    "track": "川口",
    "race_num": "4R",
    "time_str": "20:03",
    "deadline": "2026-04-21T20:03:00+09:00"
  },
  {
    "id": "静岡_12R",
    "track": "静岡",
    "race_num": "12R",
    "time_str": "20:12",
    "deadline": "2026-04-21T20:12:00+09:00"
  },
  {
    "id": "松山_12R",
    "track": "松山",
    "race_num": "12R",
    "time_str": "20:25",
    "deadline": "2026-04-21T20:25:00+09:00"
  },
  {
    "id": "川口_5R",
    "track": "川口",
    "race_num": "5R",
    "time_str": "20:28",
    "deadline": "2026-04-21T20:28:00+09:00"
  },
  {
    "id": "函館_1R",
    "track": "函館",
    "race_num": "1R",
    "time_str": "20:35",
    "deadline": "2026-04-21T20:35:00+09:00"
  },
  {
    "id": "大垣_1R",
    "track": "大垣",
    "race_num": "1R",
    "time_str": "20:45",
    "deadline": "2026-04-21T20:45:00+09:00"
  },
  {
    "id": "川口_6R",
    "track": "川口",
    "race_num": "6R",
    "time_str": "20:53",
    "deadline": "2026-04-21T20:53:00+09:00"
  },
  {
    "id": "函館_2R",
    "track": "函館",
    "race_num": "2R",
    "time_str": "20:55",
    "deadline": "2026-04-21T20:55:00+09:00"
  },
  {
    "id": "大垣_2R",
    "track": "大垣",
    "race_num": "2R",
    "time_str": "21:05",
    "deadline": "2026-04-21T21:05:00+09:00"
  },
  {
    "id": "函館_3R",
    "track": "函館",
    "race_num": "3R",
    "time_str": "21:15",
    "deadline": "2026-04-21T21:15:00+09:00"
  },
  {
    "id": "川口_7R",
    "track": "川口",
    "race_num": "7R",
    "time_str": "21:18",
    "deadline": "2026-04-21T21:18:00+09:00"
  },
  {
    "id": "大垣_3R",
    "track": "大垣",
    "race_num": "3R",
    "time_str": "21:25",
    "deadline": "2026-04-21T21:25:00+09:00"
  },
  {
    "id": "函館_4R",
    "track": "函館",
    "race_num": "4R",
    "time_str": "21:35",
    "deadline": "2026-04-21T21:35:00+09:00"
  },
  {
    "id": "大垣_4R",
    "track": "大垣",
    "race_num": "4R",
    "time_str": "21:45",
    "deadline": "2026-04-21T21:45:00+09:00"
  },
  {
    "id": "川口_8R",
    "track": "川口",
    "race_num": "8R",
    "time_str": "21:48",
    "deadline": "2026-04-21T21:48:00+09:00"
  },
  {
    "id": "函館_5R",
    "track": "函館",
    "race_num": "5R",
    "time_str": "21:55",
    "deadline": "2026-04-21T21:55:00+09:00"
  },
  {
    "id": "大垣_5R",
    "track": "大垣",
    "race_num": "5R",
    "time_str": "22:05",
    "deadline": "2026-04-21T22:05:00+09:00"
  },
  {
    "id": "函館_6R",
    "track": "函館",
    "race_num": "6R",
    "time_str": "22:15",
    "deadline": "2026-04-21T22:15:00+09:00"
  },
  {
    "id": "大垣_6R",
    "track": "大垣",
    "race_num": "6R",
    "time_str": "22:25",
    "deadline": "2026-04-21T22:25:00+09:00"
  },
  {
    "id": "函館_7R",
    "track": "函館",
    "race_num": "7R",
    "time_str": "22:35",
    "deadline": "2026-04-21T22:35:00+09:00"
  },
  {
    "id": "大垣_7R",
    "track": "大垣",
    "race_num": "7R",
    "time_str": "22:45",
    "deadline": "2026-04-21T22:45:00+09:00"
  },
  {
    "id": "函館_8R",
    "track": "函館",
    "race_num": "8R",
    "time_str": "22:55",
    "deadline": "2026-04-21T22:55:00+09:00"
  },
  {
    "id": "大垣_8R",
    "track": "大垣",
    "race_num": "8R",
    "time_str": "23:05",
    "deadline": "2026-04-21T23:05:00+09:00"
  },
  {
    "id": "函館_9R",
    "track": "函館",
    "race_num": "9R",
    "time_str": "23:15",
    "deadline": "2026-04-21T23:15:00+09:00"
  },
  {
    "id": "大垣_9R",
    "track": "大垣",
    "race_num": "9R",
    "time_str": "23:25",
    "deadline": "2026-04-21T23:25:00+09:00"
  }
]