[
  {
    "id": "熊本_3R",
    "track": "熊本",
    "race_num": "3R",
    "time_str": "09:15",
    "deadline": "2026-04-16T09:15:00+09:00"
  },
  {
    "id": "高知_4R",
    "track": "高知",
    "race_num": "4R",
    "time_str": "09:25",
    "deadline": "2026-04-16T09:25:00+09:00"
  },
  {
    "id": "熊本_4R",
    "track": "熊本",
    "race_num": "4R",
    "time_str": "09:35",
    "deadline": "2026-04-16T09:35:00+09:00"
  },
  {
    "id": "高知_5R",
    "track": "高知",
    "race_num": "5R",
    "time_str": "09:45",
    "deadline": "2026-04-16T09:45:00+09:00"
  },
  {
    "id": "熊本_5R",
    "track": "熊本",
    "race_num": "5R",
    "time_str": "09:55",
    "deadline": "2026-04-16T09:55:00+09:00"
  },
  {
    "id": "高知_6R",
    "track": "高知",
    "race_num": "6R",
    "time_str": "10:05",
    "deadline": "2026-04-16T10:05:00+09:00"
  },
  {
    "id": "熊本_6R",
    "track": "熊本",
    "race_num": "6R",
    "time_str": "10:15",
    "deadline": "2026-04-16T10:15:00+09:00"
  },
  {
    "id": "高知_7R",
    "track": "高知",
    "race_num": "7R",
    "time_str": "10:25",
    "deadline": "2026-04-16T10:25:00+09:00"
  },
  {
    "id": "熊本_7R",
    "track": "熊本",
    "race_num": "7R",
    "time_str": "10:35",
    "deadline": "2026-04-16T10:35:00+09:00"
  },
  {
    "id": "豊橋_1R",
    "track": "豊橋",
    "race_num": "1R",
    "time_str": "10:40",
    "deadline": "2026-04-16T10:40:00+09:00"
  },
  {
    "id": "取手_1R",
    "track": "取手",
    "race_num": "1R",
    "time_str": "10:53",
    "deadline": "2026-04-16T10:53:00+09:00"
  },
  {
    "id": "浜松_1R",
    "track": "浜松",
    "race_num": "1R",
    "time_str": "10:54",
    "deadline": "2026-04-16T10:54:00+09:00"
  },
  {
    "id": "豊橋_2R",
    "track": "豊橋",
    "race_num": "2R",
    "time_str": "11:07",
    "deadline": "2026-04-16T11:07:00+09:00"
  },
  {
    "id": "浜松_2R",
    "track": "浜松",
    "race_num": "2R",
    "time_str": "11:19",
    "deadline": "2026-04-16T11:19:00+09:00"
  },
  {
    "id": "取手_2R",
    "track": "取手",
    "race_num": "2R",
    "time_str": "11:21",
    "deadline": "2026-04-16T11:21:00+09:00"
  },
  {
    "id": "豊橋_3R",
    "track": "豊橋",
    "race_num": "3R",
    "time_str": "11:35",
    "deadline": "2026-04-16T11:35:00+09:00"
  },
  {
    "id": "浜松_3R",
    "track": "浜松",
    "race_num": "3R",
    "time_str": "11:45",
    "deadline": "2026-04-16T11:45:00+09:00"
  },
  {
    "id": "取手_3R",
    "track": "取手",
    "race_num": "3R",
    "time_str": "11:49",
    "deadline": "2026-04-16T11:49:00+09:00"
  },
  {
    "id": "豊橋_4R",
    "track": "豊橋",
    "race_num": "4R",
    "time_str": "12:03",
    "deadline": "2026-04-16T12:03:00+09:00"
  },
  {
    "id": "浜松_4R",
    "track": "浜松",
    "race_num": "4R",
    "time_str": "12:13",
    "deadline": "2026-04-16T12:13:00+09:00"
  },
  {
    "id": "取手_4R",
    "track": "取手",
    "race_num": "4R",
    "time_str": "12:17",
    "deadline": "2026-04-16T12:17:00+09:00"
  },
  {
    "id": "豊橋_5R",
    "track": "豊橋",
    "race_num": "5R",
    "time_str": "12:31",
    "deadline": "2026-04-16T12:31:00+09:00"
  },
  {
    "id": "浜松_5R",
    "track": "浜松",
    "race_num": "5R",
    "time_str": "12:44",
    "deadline": "2026-04-16T12:44:00+09:00"
  },
  {
    "id": "取手_5R",
    "track": "取手",
    "race_num": "5R",
    "time_str": "12:45",
    "deadline": "2026-04-16T12:45:00+09:00"
  },
  {
    "id": "豊橋_6R",
    "track": "豊橋",
    "race_num": "6R",
    "time_str": "12:59",
    "deadline": "2026-04-16T12:59:00+09:00"
  },
  {
    "id": "取手_6R",
    "track": "取手",
    "race_num": "6R",
    "time_str": "13:13",
    "deadline": "2026-04-16T13:13:00+09:00"
  },
  {
    "id": "浜松_6R",
    "track": "浜松",
    "race_num": "6R",
    "time_str": "13:14",
    "deadline": "2026-04-16T13:14:00+09:00"
  },
  {
    "id": "豊橋_7R",
    "track": "豊橋",
    "race_num": "7R",
    "time_str": "13:27",
    "deadline": "2026-04-16T13:27:00+09:00"
  },
  {
    "id": "取手_7R",
    "track": "取手",
    "race_num": "7R",
    "time_str": "13:41",
    "deadline": "2026-04-16T13:41:00+09:00"
  },
  {
    "id": "浜松_7R",
    "track": "浜松",
    "race_num": "7R",
    "time_str": "13:44",
    "deadline": "2026-04-16T13:44:00+09:00"
  },
  {
    "id": "豊橋_8R",
    "track": "豊橋",
    "race_num": "8R",
    "time_str": "13:55",
    "deadline": "2026-04-16T13:55:00+09:00"
  },
  {
    "id": "取手_8R",
    "track": "取手",
    "race_num": "8R",
    "time_str": "14:09",
    "deadline": "2026-04-16T14:09:00+09:00"
  },
  {
    "id": "浜松_8R",
    "track": "浜松",
    "race_num": "8R",
    "time_str": "14:14",
    "deadline": "2026-04-16T14:14:00+09:00"
  },
  {
    "id": "豊橋_9R",
    "track": "豊橋",
    "race_num": "9R",
    "time_str": "14:23",
    "deadline": "2026-04-16T14:23:00+09:00"
  },
  {
    "id": "取手_9R",
    "track": "取手",
    "race_num": "9R",
    "time_str": "14:37",
    "deadline": "2026-04-16T14:37:00+09:00"
  },
  {
    "id": "浜松_9R",
    "track": "浜松",
    "race_num": "9R",
    "time_str": "14:45",
    "deadline": "2026-04-16T14:45:00+09:00"
  },
  {
    "id": "豊橋_10R",
    "track": "豊橋",
    "race_num": "10R",
    "time_str": "14:51",
    "deadline": "2026-04-16T14:51:00+09:00"
  },
  {
    "id": "取手_10R",
    "track": "取手",
    "race_num": "10R",
    "time_str": "15:05",
    "deadline": "2026-04-16T15:05:00+09:00"
  },
  {
    "id": "浜松_10R",
    "track": "浜松",
    "race_num": "10R",
    "time_str": "15:16",
    "deadline": "2026-04-16T15:16:00+09:00"
  },
  {
    "id": "豊橋_11R",
    "track": "豊橋",
    "race_num": "11R",
    "time_str": "15:20",
    "deadline": "2026-04-16T15:20:00+09:00"
  },
  {
    "id": "取手_11R",
    "track": "取手",
    "race_num": "11R",
    "time_str": "15:33",
    "deadline": "2026-04-16T15:33:00+09:00"
  },
  {
    "id": "函館_1R",
    "track": "函館",
    "race_num": "1R",
    "time_str": "15:41",
    "deadline": "2026-04-16T15:41:00+09:00"
  },
  {
    "id": "豊橋_12R",
    "track": "豊橋",
    "race_num": "12R",
    "time_str": "15:50",
    "deadline": "2026-04-16T15:50:00+09:00"
  },
  {
    "id": "浜松_11R",
    "track": "浜松",
    "race_num": "11R",
    "time_str": "15:54",
    "deadline": "2026-04-16T15:54:00+09:00"
  },
  {
    "id": "函館_2R",
    "track": "函館",
    "race_num": "2R",
    "time_str": "16:03",
    "deadline": "2026-04-16T16:03:00+09:00"
  },
  {
    "id": "取手_12R",
    "track": "取手",
    "race_num": "12R",
    "time_str": "16:10",
    "deadline": "2026-04-16T16:10:00+09:00"
  },
  {
    "id": "函館_3R",
    "track": "函館",
    "race_num": "3R",
    "time_str": "16:28",
    "deadline": "2026-04-16T16:28:00+09:00"
  },
  {
    "id": "浜松_12R",
    "track": "浜松",
    "race_num": "12R",
    "time_str": "16:33",
    "deadline": "2026-04-16T16:33:00+09:00"
  },
  {
    "id": "函館_4R",
    "track": "函館",
    "race_num": "4R",
    "time_str": "16:53",
    "deadline": "2026-04-16T16:53:00+09:00"
  },
  {
    "id": "函館_5R",
    "track": "函館",
    "race_num": "5R",
    "time_str": "17:19",
    "deadline": "2026-04-16T17:19:00+09:00"
  },
  {
    "id": "函館_6R",
    "track": "函館",
    "race_num": "6R",
    "time_str": "17:45",
    "deadline": "2026-04-16T17:45:00+09:00"
  },
  {
    "id": "函館_7R",
    "track": "函館",
    "race_num": "7R",
    "time_str": "18:11",
    "deadline": "2026-04-16T18:11:00+09:00"
  },
  {
    "id": "函館_8R",
    "track": "函館",
    "race_num": "8R",
    "time_str": "18:37",
    "deadline": "2026-04-16T18:37:00+09:00"
  },
  {
    "id": "函館_9R",
    "track": "函館",
    "race_num": "9R",
    "time_str": "19:04",
    "deadline": "2026-04-16T19:04:00+09:00"
  },
  {
    "id": "函館_10R",
    "track": "函館",
    "race_num": "10R",
    "time_str": "19:31",
    "deadline": "2026-04-16T19:31:00+09:00"
  },
  {
    "id": "函館_11R",
    "track": "函館",
    "race_num": "11R",
    "time_str": "19:58",
    "deadline": "2026-04-16T19:58:00+09:00"
  },
  {
    "id": "飯塚_1R",
    "track": "飯塚",
    "race_num": "1R",
    "time_str": "20:17",
    "deadline": "2026-04-16T20:17:00+09:00"
  },
  {
    "id": "函館_12R",
    "track": "函館",
    "race_num": "12R",
    "time_str": "20:25",
    "deadline": "2026-04-16T20:25:00+09:00"
  },
  {
    "id": "松戸_1R",
    "track": "松戸",
    "race_num": "1R",
    "time_str": "20:35",
    "deadline": "2026-04-16T20:35:00+09:00"
  },
  {
    "id": "岐阜_1R",
    "track": "岐阜",
    "race_num": "1R",
    "time_str": "20:45",
    "deadline": "2026-04-16T20:45:00+09:00"
  },
  {
    "id": "飯塚_2R",
    "track": "飯塚",
    "race_num": "2R",
    "time_str": "20:45",
    "deadline": "2026-04-16T20:45:00+09:00"
  },
  {
    "id": "松戸_2R",
    "track": "松戸",
    "race_num": "2R",
    "time_str": "20:55",
    "deadline": "2026-04-16T20:55:00+09:00"
  },
  {
    "id": "岐阜_2R",
    "track": "岐阜",
    "race_num": "2R",
    "time_str": "21:05",
    "deadline": "2026-04-16T21:05:00+09:00"
  },
  {
    "id": "飯塚_3R",
    "track": "飯塚",
    "race_num": "3R",
    "time_str": "21:13",
    "deadline": "2026-04-16T21:13:00+09:00"
  },
  {
    "id": "松戸_3R",
    "track": "松戸",
    "race_num": "3R",
    "time_str": "21:15",
    "deadline": "2026-04-16T21:15:00+09:00"
  },
  {
    "id": "岐阜_3R",
    "track": "岐阜",
    "race_num": "3R",
    "time_str": "21:25",
    "deadline": "2026-04-16T21:25:00+09:00"
  },
  {
    "id": "松戸_4R",
    "track": "松戸",
    "race_num": "4R",
    "time_str": "21:35",
    "deadline": "2026-04-16T21:35:00+09:00"
  },
  {
    "id": "飯塚_4R",
    "track": "飯塚",
    "race_num": "4R",
    "time_str": "21:42",
    "deadline": "2026-04-16T21:42:00+09:00"
  },
  {
    "id": "岐阜_4R",
    "track": "岐阜",
    "race_num": "4R",
    "time_str": "21:45",
    "deadline": "2026-04-16T21:45:00+09:00"
  },
  {
    "id": "松戸_5R",
    "track": "松戸",
    "race_num": "5R",
    "time_str": "21:55",
    "deadline": "2026-04-16T21:55:00+09:00"
  },
  {
    "id": "岐阜_5R",
    "track": "岐阜",
    "race_num": "5R",
    "time_str": "22:05",
    "deadline": "2026-04-16T22:05:00+09:00"
  },
  {
    "id": "飯塚_5R",
    "track": "飯塚",
    "race_num": "5R",
    "time_str": "22:11",
    "deadline": "2026-04-16T22:11:00+09:00"
  },
  {
    "id": "松戸_6R",
    "track": "松戸",
    "race_num": "6R",
    "time_str": "22:15",
    "deadline": "2026-04-16T22:15:00+09:00"
  },
  {
    "id": "岐阜_6R",
    "track": "岐阜",
    "race_num": "6R",
    "time_str": "22:25",
    "deadline": "2026-04-16T22:25:00+09:00"
  },
  {
    "id": "松戸_7R",
    "track": "松戸",
    "race_num": "7R",
    "time_str": "22:35",
    "deadline": "2026-04-16T22:35:00+09:00"
  },
  {
    "id": "飯塚_6R",
    "track": "飯塚",
    "race_num": "6R",
    "time_str": "22:41",
    "deadline": "2026-04-16T22:41:00+09:00"
  },
  {
    "id": "岐阜_7R",
    "track": "岐阜",
    "race_num": "7R",
    "time_str": "22:45",
    "deadline": "2026-04-16T22:45:00+09:00"
  },
  {
    "id": "松戸_8R",
    "track": "松戸",
    "race_num": "8R",
    "time_str": "22:55",
    "deadline": "2026-04-16T22:55:00+09:00"
  },
  {
    "id": "岐阜_8R",
    "track": "岐阜",
    "race_num": "8R",
    "time_str": "23:05",
    "deadline": "2026-04-16T23:05:00+09:00"
  },
  {
    "id": "飯塚_7R",
    "track": "飯塚",
    "race_num": "7R",
    "time_str": "23:11",
    "deadline": "2026-04-16T23:11:00+09:00"
  },
  {
    "id": "松戸_9R",
    "track": "松戸",
    "race_num": "9R",
    "time_str": "23:15",
    "deadline": "2026-04-16T23:15:00+09:00"
  },
  {
    "id": "岐阜_9R",
    "track": "岐阜",
    "race_num": "9R",
    "time_str": "23:25",
    "deadline": "2026-04-16T23:25:00+09:00"
  },
  {
    "id": "飯塚_8R",
    "track": "飯塚",
    "race_num": "8R",
    "time_str": "23:43",
    "deadline": "2026-04-16T23:43:00+09:00"
  }
]